hdfs/__init__.py
hdfs/__main__.py
hdfs/client.py
hdfs/config.py
hdfs/util.py
hdfs/ext/__init__.py
hdfs/ext/dataframe.py
hdfs/ext/kerberos.py
hdfs/ext/avro/__init__.py
hdfs/ext/avro/__main__.py
hdfs-2.5.7.dist-info/AUTHORS
hdfs-2.5.7.dist-info/LICENSE
hdfs-2.5.7.dist-info/METADATA
hdfs-2.5.7.dist-info/WHEEL
hdfs-2.5.7.dist-info/entry_points.txt
hdfs-2.5.7.dist-info/top_level.txt
hdfs-2.5.7.dist-info/RECORD
