Metadata-Version: 2.1
Name: hdfs
Version: 2.5.7
Summary: HdfsCLI: API and command line interface for HDFS.
Home-page: https://hdfscli.readthedocs.io
Author: Matthieu Monsch
Author-email: mtth@apache.org
License: MIT
Platform: UNKNOWN
Classifier: Development Status :: 5 - Production/Stable
Classifier: Intended Audience :: Developers
Classifier: License :: OSI Approved :: MIT License
Classifier: Programming Language :: Python
Classifier: Programming Language :: Python :: 2.6
Classifier: Programming Language :: Python :: 2.7
Classifier: Programming Language :: Python :: 3.3
Classifier: Programming Language :: Python :: 3.4
Classifier: Programming Language :: Python :: 3.5
Classifier: Programming Language :: Python :: 3.6
Requires-Dist: docopt
Requires-Dist: requests (>=2.7.0)
Requires-Dist: six (>=1.9.0)
Provides-Extra: avro
Requires-Dist: fastavro (>=0.21.19); extra == 'avro'
Provides-Extra: dataframe
Requires-Dist: fastavro (>=0.21.19); extra == 'dataframe'
Requires-Dist: pandas (>=0.14.1); extra == 'dataframe'
Provides-Extra: kerberos
Requires-Dist: requests-kerberos (>=0.7.0); extra == 'kerberos'
